scrapethat/__init__.py
scrapethat/main.py
scrapethat-1.0.3.dist-info/METADATA
scrapethat-1.0.3.dist-info/WHEEL
scrapethat-1.0.3.dist-info/top_level.txt
scrapethat-1.0.3.dist-info/RECORD
