Metadata-Version: 2.1
Name: scrapethat
Version: 1.0.3
Summary: Tools for faster scraping
Home-page: https://github.com/misrori/scrapethat
Author: Mihaly Orsos
Author-email: ormraat.pte@gmail.com
License: MIT
Platform: UNKNOWN
Requires-Dist: bs4
Requires-Dist: requests
Requires-Dist: pandas
Requires-Dist: cloudscraper
